open_kimi/__init__.py
open_kimi/kimi_linear.py
open_kimi/mla.py
open_kimi/model.py
open_kimi/moe.py
open_kimi-0.1.2.dist-info/LICENSE
open_kimi-0.1.2.dist-info/METADATA
open_kimi-0.1.2.dist-info/WHEEL
open_kimi-0.1.2.dist-info/RECORD
