Metadata-Version: 2.3
Name: open-kimi
Version: 0.1.2
Summary: An open source implementation of the Kimi K2 Reasoning model architecture in pure PyTorch
License: MIT
Keywords: artificial intelligence,deep learning,kimi,kimi-k2,k2-thinking,moonshot-ai,llms,transformers,pytorch,language-models,reasoning-models,mixture-of-experts,moe,mla,attention-mechanisms
Author: Kye Gomez
Author-email: kye@swarms.world
Requires-Python: >=3.10,<4.0
Classifier: Development Status :: 4 - Beta
Classifier: Intended Audience :: Developers
Classifier: License :: OSI Approved :: MIT License
Classifier: Programming Language :: Python :: 3
Classifier: Programming Language :: Python :: 3.10
Classifier: Programming Language :: Python :: 3.11
Classifier: Programming Language :: Python :: 3.12
Classifier: Programming Language :: Python :: 3.13
Classifier: Topic :: Scientific/Engineering :: Artificial Intelligence
Requires-Dist: einops
Requires-Dist: torch
Project-URL: Documentation, https://github.com/kyegomez/Open-Kimi
Project-URL: Homepage, https://github.com/kyegomez/Open-Kimi
Project-URL: Repository, https://github.com/kyegomez/Open-Kimi
